iosbuildversions/__init__.py
iosbuildversions/builds.py
iosbuildversions/scraper.py
iosbuildversions-0.4.0.dist-info/DESCRIPTION.rst
iosbuildversions-0.4.0.dist-info/METADATA
iosbuildversions-0.4.0.dist-info/RECORD
iosbuildversions-0.4.0.dist-info/WHEEL
iosbuildversions-0.4.0.dist-info/metadata.json
iosbuildversions-0.4.0.dist-info/top_level.txt
